meomaya/.gitignore
meomaya/LICENSE
meomaya/README.md
meomaya/__init__.py
meomaya/__main__.py
meomaya/pyproject.toml
meomaya/requirements.txt
meomaya/api/__init__.py
meomaya/api/server.py
meomaya/audio/__init__.py
meomaya/audio/pipeline.py
meomaya/cli/__init__.py
meomaya/cli/meomaya_cmd.py
meomaya/core/__init__.py
meomaya/core/cython_tagger.pyx
meomaya/core/hardware.py
meomaya/core/hf_local.py
meomaya/core/model_registry.py
meomaya/core/modelify.py
meomaya/core/normalizer.py
meomaya/core/parser.py
meomaya/core/tagger.py
meomaya/core/tokenizer.py
meomaya/core/utils.py
meomaya/data/__init__.py
meomaya/data/corpus_loader.py
meomaya/data/datasets/sample.meydata
meomaya/dist/meomaya-0.1.0.tar.gz
meomaya/docs/index.md
meomaya/examples/full_nlp_workflow_demo.py
meomaya/image/__init__.py
meomaya/image/pipeline.py
meomaya/ml/__init__.py
meomaya/ml/classifier.py
meomaya/ml/vectorizer.py
meomaya/scripts/eval_classifier.py
meomaya/scripts/train_classifier.py
meomaya/tests/test_all.py
meomaya/text/__init__.py
meomaya/text/pipeline.py
meomaya/video/__init__.py
meomaya/video/pipeline.py
meomaya-0.1.0.dist-info/WHEEL
meomaya-0.1.0.dist-info/METADATA
meomaya-0.1.0.dist-info/RECORD
