Metadata-Version: 2.4
Name: meomaya
Version: 0.1.0
Summary: MeoMaya package initialization.
Home-page: https://github.com/KashyapSinh-Gohil/MeoMaya
Author: Kashyapsinh Gohil
Author-email: Kagohil000@gmail.com
Requires-Python: >=3.11
